science_tools/__init__.py
science_tools/_version.py
science_tools/py.typed
science_tools/science_tools.py
science_tools/tests/__init__.py
science_tools/tests/test_science_tools.py
science_tools-0.0.2.dist-info/LICENSE
science_tools-0.0.2.dist-info/METADATA
science_tools-0.0.2.dist-info/WHEEL
science_tools-0.0.2.dist-info/top_level.txt
science_tools-0.0.2.dist-info/RECORD
